eeslib/__init__.py
eeslib/boiling.py
eeslib/external_flow.py
eeslib/fin_efficiency.py
eeslib/fluid_properties.py
eeslib/functions.py
eeslib/heat_exchangers.py
eeslib/internal_flow.py
eeslib/lookup_data.py
eeslib/radiation.py
eeslib/talbot_inversion.py
eeslib-0.0.4.dist-info/licenses/LICENSE
eeslib-0.0.4.dist-info/METADATA
eeslib-0.0.4.dist-info/WHEEL
eeslib-0.0.4.dist-info/top_level.txt
eeslib-0.0.4.dist-info/RECORD
