Metadata-Version: 2.4
Name: eeslib
Version: 0.0.4
Summary: A Python library for heat transfer and thermodynamics calculations, derived from EES
Author-email: Mike Wagner <mjwagner2@wisc.edu>
License-Expression: LicenseRef-UW-Madison-proprietary-instructional
Project-URL: Homepage, https://github.com/eeslib/eeslib
Project-URL: Issues, https://github.com/eeslib/eeslib/issues
Classifier: Programming Language :: Python :: 3
Classifier: Operating System :: OS Independent
Classifier: Topic :: Scientific/Engineering :: Physics
Classifier: Topic :: Education
Requires-Python: >=3.9
License-File: LICENSE
Requires-Dist: numpy>=1.21.0
Requires-Dist: scipy>=1.7.0
Requires-Dist: CoolProp>=6.4.0
Requires-Dist: sympy>=1.13.0
Requires-Dist: markdown-pdf>=1.3.0
Requires-Dist: PyLaTeX>=1.4.0
Requires-Dist: PyMuPDF>=1.24.0
Requires-Dist: pandas>=1.3.0
Requires-Dist: matplotlib>=3.10.0
Provides-Extra: dev
Requires-Dist: pytest>=7.0.0; extra == "dev"
Requires-Dist: pytest-cov>=4.0.0; extra == "dev"
Requires-Dist: build>=0.10; extra == "dev"
Requires-Dist: twine>=4.0.0; extra == "dev"
Requires-Dist: sphinx>=8.2.3; extra == "dev"
Requires-Dist: sphinx_rtd_theme>=3.0.2; extra == "dev"
Requires-Dist: sphinx_autodoc_typehints>=3.5.2; extra == "dev"
Provides-Extra: admin
Requires-Dist: wxpython>=4.2.4; extra == "admin"
Requires-Dist: canvasapi>=3.4.0; extra == "admin"
Dynamic: license-file
